qreu/__init__.py
qreu/address.py
qreu/email.py
qreu/local.py
qreu/sendcontext.py
qreu-0.13.3.dist-info/LICENSE
qreu-0.13.3.dist-info/METADATA
qreu-0.13.3.dist-info/WHEEL
qreu-0.13.3.dist-info/top_level.txt
qreu-0.13.3.dist-info/RECORD
