Metadata-Version: 2.2
Name: qreu
Version: 0.13.3
Summary: EMail Wrapper
Home-page: https://github.com/gisce/qreu
Author: GISCE-TI, S.L.
Author-email: devel@gisce.net
License: MIT
Classifier: Programming Language :: Python :: 2.7
Classifier: Programming Language :: Python :: 3.5
Classifier: Topic :: Software Development :: Libraries
Classifier: Topic :: Communications :: Email
License-File: LICENSE
Requires-Dist: html2text
Requires-Dist: six
Requires-Dist: unidecode
Dynamic: author
Dynamic: author-email
Dynamic: classifier
Dynamic: description
Dynamic: home-page
Dynamic: license
Dynamic: requires-dist
Dynamic: summary
